handouter/__init__.py
handouter/__main__.py
handouter/gen.py
handouter/pack.py
handouter/tex_internals.py
handouter/utils.py
handouter/version.py
handouter-0.0.16.dist-info/licenses/LICENSE.md
handouter-0.0.16.dist-info/._PKG-INFO
handouter-0.0.16.dist-info/._SOURCES.txt
handouter-0.0.16.dist-info/._dependency_links.txt
handouter-0.0.16.dist-info/._entry_points.txt
handouter-0.0.16.dist-info/._requires.txt
handouter-0.0.16.dist-info/._top_level.txt
handouter-0.0.16.dist-info/METADATA
handouter-0.0.16.dist-info/WHEEL
handouter-0.0.16.dist-info/entry_points.txt
handouter-0.0.16.dist-info/top_level.txt
handouter-0.0.16.dist-info/RECORD
