Metadata-Version: 2.4
Name: handouter
Version: 0.0.16
Summary: Handouter is a script that wraps tectonic to generate handouts for [Chgk](https://en.wikipedia.org/wiki/What%3F_Where%3F_When%3F)
Home-page: https://gitlab.com/peczony/handouter
Author: Alexander Pecheny
Author-email: ap@pecheny.me
Classifier: Programming Language :: Python :: 3
Classifier: License :: OSI Approved :: MIT License
Classifier: Operating System :: OS Independent
License-File: LICENSE.md
Requires-Dist: pecheny_utils>=0.0.8
Requires-Dist: watchdog
Requires-Dist: toml
Provides-Extra: full
Requires-Dist: chgksuite; extra == "full"
Requires-Dist: pypdf; extra == "full"
Dynamic: author
Dynamic: author-email
Dynamic: classifier
Dynamic: description
Dynamic: description-content-type
Dynamic: home-page
Dynamic: license-file
Dynamic: provides-extra
Dynamic: requires-dist
Dynamic: summary
